quantifier/__init__.py
quantifier/main.py
quantifier/quantify.py
advCounter-0.0.2.dist-info/METADATA
advCounter-0.0.2.dist-info/WHEEL
advCounter-0.0.2.dist-info/top_level.txt
advCounter-0.0.2.dist-info/RECORD
